custom_pyvi/ViTokenizer.py
custom_pyvi/__init__.py
custom_pyvi/models/custom_pyvi3.pkl
custom_pyvi/models/custom_words.txt
custom_pyvi-1.0.9.dist-info/licenses/License
custom_pyvi-1.0.9.dist-info/METADATA
custom_pyvi-1.0.9.dist-info/WHEEL
custom_pyvi-1.0.9.dist-info/top_level.txt
custom_pyvi-1.0.9.dist-info/RECORD
