Metadata-Version: 2.4
Name: custom-pyvi
Version: 1.0.9
Summary: Một phiên bản tùy chỉnh của ViTokenizer để xử lý Tiếng Việt hiệu quả cho các dự án cụ thể.
Author-email: Chill4Share <chill4share@gmail.com>
License: MIT License
Keywords: vi-tokenizer,vietnamese nlp,word segmentation,custom
Classifier: Development Status :: 5 - Production/Stable
Classifier: Intended Audience :: Developers
Classifier: License :: OSI Approved :: MIT License
Classifier: Operating System :: OS Independent
Classifier: Programming Language :: Python :: 3
Classifier: Topic :: Text Processing :: Linguistic
Requires-Python: >=3.8
License-File: License
Requires-Dist: scikit-learn
Requires-Dist: sklearn-crfsuite
Dynamic: license-file
